[
    {
        "author": "ho Spike",
        "comment": "It's totally amazing watch face, I love it",
        "date": "March 16, 2016",
        "permlink": "/store/apps/details?id=com.qmzc.timagine.watchface.earthpro&reviewId=Z3A6QU9xcFRPRnhJX3J4aUlJMXExVW9TMnhXeDQxRm1pc25oTHdJQVdCTThLajVuY1p1MUNFak53Vk0yclVpZ3R3b2dobktremJUdEhyandBT3dGV20xTHc",
        "reply": null,
        "star": 5,
        "title": null
    },
    {
        "author": "Aung Wai Phyo",
        "comment": "Lovely watchface...try it...",
        "date": "March 15, 2016",
        "permlink": "/store/apps/details?id=com.qmzc.timagine.watchface.earthpro&reviewId=Z3A6QU9xcFRPR3NVdXZObG9kNktOb1owY09LVGJMUFMwTlJoWTNzUFpaSTVpZFJvOFF5amQ1YWd6ZC02ZkI4SllCaGJnSXFOSGswYkdmMkVtdlVOSEN0Smc",
        "reply": {
            "author": "Timagine",
            "content": "We are sooooo delighted that you like it!!!",
            "date": "March 15, 2016"
        },
        "star": 5,
        "title": "Cool watch face"
    }
]