{
    "title": "Offline Jízdní řády CG Transit",
    "summary": "The new version of the offline timetables in &quot;material design&quot; with the support of Android Wear!",
    "icon": "//lh5.ggpht.com/_cJB2b8bI362g6mxM_fotryQWH6TtKMm91qYZE8KEJbwxqJJH-QblWV7Nmt3xh7ksT4=w300",
    "price": "0",
    "free": true,
    "minInstalls": 100000,
    "maxInstalls": 500000,
    "score": 4.6,
    "reviews": 7169,
    "developer": "circlegate",
    "developerId": "circlegate",
    "developerEmail": "android@cgtransit.com",
    "developerWebsite": "http://www.cgtransit.cz",
    "developerAddress": "U Valchy 486\n53703 Chrudim\nCzech Republic",
    "updated": "September 7, 2017",
    "version": "3.1.4",
    "genre": "Maps & Navigation",
    "genreId": "MAPS_AND_NAVIGATION",
    "description": "CG Transit umožňuje offline vyhledávání v jízdních řádech vlaků, autobusů a MHD v ČR a SK.Offline vyhledávání znamená výhodu nejen pro uživatele bez datového tarifu, ale hodí se všem, kdo potřebují často a rychle vyhledávat v jízdních řádech v místech se špatným pokrytím - tedy např. při cestování vlakem, metrem apod.Aplikace nabízí moderní, propracované rozhraní, které je přizpůsobené i pro tablety a nově také pro hodinky na platformě Android Wear. Kromě klasického vyhledávání spojení umožňuje také naplánovat si trasu na mapě, zobrazit odjezdy spojů z blízkých zastávek nebo vyhledání linky podle jména.Klíčové vlastnosti:★ Atraktivní \"Material\" design aplikace★ Funkce \"Vyhledávání spojení\": Klasické vyhledávání spojení Odkud → (Přes) → Kam★ Funkce \"Hledání na mapě\": Vyhledávání spojení na mapě v dvoupanelovém rozhraní★ Funkce \"Odjezdy ze zastávek\": Rychlé zobrazení zastávek s odjezdy spojů v okolí nebo ze zadaného místa★ Funkce \"Seznam linek\": Seznam linek resp. spojů v jízdním řádů s možností vyhledávání podle názvu linky a se všemi potřebnými informacemi★ Pokročilý našeptávač zastávek a adresních bodů s chytrým řazením, se zobrazováním čísel linek u zastávek MHD a s možností uložení adresy pod vlastním názvem (Doma, Práce...)★ Automatické aktualizace jízdních řádů přes Wi-Fi★ Přizpůsobení pro tablety★ Samostatná aplikace pro hodinky Android WearData poskytují společnosti CHAPS spol. s r.o. a Inprop s.r.o.Za vytvoření seznamu GPS souřadnic pro MHD Košice děkujeme uživateli Júliu Kundrátovi.CENA:Samotná aplikace je k dispozici ke stažení zdarma. Za datové soubory jízdních řádů se platí roční licenční poplatek. Jízdní řády je možné nakupovat buď jednotlivě nebo je možné zakoupit zvýhodněné balíčky pro Českou a Slovenskou republiku a evropské vlaky. Aktuální ceník naleznete na webových stránkách aplikace:http://www.cgtransit.czAKCE - noví uživatelé mají měsíc na vyzkoušení všech jízdních řádů zdarma*** Pokud máte s aplikací problém, napište nám prosím na email android@cgtransit.com - pokud napíšete problém do hodnocení aplikace, nemůžeme ho vyřešit. Díky. ***",
    "descriptionHTML": "CG Transit umo&#x17E;&#x148;uje offline vyhled&#xE1;v&#xE1;n&#xED; v j&#xED;zdn&#xED;ch &#x159;&#xE1;dech vlak&#x16F;, autobus&#x16F; a MHD v &#x10C;R a SK.<br>Offline vyhled&#xE1;v&#xE1;n&#xED; znamen&#xE1; v&#xFD;hodu nejen pro u&#x17E;ivatele bez datov&#xE9;ho tarifu, ale hod&#xED; se v&#x161;em, kdo pot&#x159;ebuj&#xED; &#x10D;asto a rychle vyhled&#xE1;vat v j&#xED;zdn&#xED;ch &#x159;&#xE1;dech v m&#xED;stech se &#x161;patn&#xFD;m pokryt&#xED;m - tedy nap&#x159;. p&#x159;i cestov&#xE1;n&#xED; vlakem, metrem apod.<br><br>Aplikace nab&#xED;z&#xED; modern&#xED;, propracovan&#xE9; rozhran&#xED;, kter&#xE9; je p&#x159;izp&#x16F;soben&#xE9; i pro tablety a nov&#x11B; tak&#xE9; pro hodinky na platform&#x11B; Android Wear. Krom&#x11B; klasick&#xE9;ho vyhled&#xE1;v&#xE1;n&#xED; spojen&#xED; umo&#x17E;&#x148;uje tak&#xE9; napl&#xE1;novat si trasu na map&#x11B;, zobrazit odjezdy spoj&#x16F; z bl&#xED;zk&#xFD;ch zast&#xE1;vek nebo vyhled&#xE1;n&#xED; linky podle jm&#xE9;na.<br><br>Kl&#xED;&#x10D;ov&#xE9; vlastnosti:<br>&#x2605; Atraktivn&#xED; &quot;Material&quot; design aplikace<br>&#x2605; Funkce &quot;Vyhled&#xE1;v&#xE1;n&#xED; spojen&#xED;&quot;: Klasick&#xE9; vyhled&#xE1;v&#xE1;n&#xED; spojen&#xED; Odkud &#x2192; (P&#x159;es) &#x2192; Kam<br>&#x2605; Funkce &quot;Hled&#xE1;n&#xED; na map&#x11B;&quot;: Vyhled&#xE1;v&#xE1;n&#xED; spojen&#xED; na map&#x11B; v dvoupanelov&#xE9;m rozhran&#xED;<br>&#x2605; Funkce &quot;Odjezdy ze zast&#xE1;vek&quot;: Rychl&#xE9; zobrazen&#xED; zast&#xE1;vek s odjezdy spoj&#x16F; v okol&#xED; nebo ze zadan&#xE9;ho m&#xED;sta<br>&#x2605; Funkce &quot;Seznam linek&quot;: Seznam linek resp. spoj&#x16F; v j&#xED;zdn&#xED;m &#x159;&#xE1;d&#x16F; s mo&#x17E;nost&#xED; vyhled&#xE1;v&#xE1;n&#xED; podle n&#xE1;zvu linky a se v&#x161;emi pot&#x159;ebn&#xFD;mi informacemi<br>&#x2605; Pokro&#x10D;il&#xFD; na&#x161;ept&#xE1;va&#x10D; zast&#xE1;vek a adresn&#xED;ch bod&#x16F; s chytr&#xFD;m &#x159;azen&#xED;m, se zobrazov&#xE1;n&#xED;m &#x10D;&#xED;sel linek u zast&#xE1;vek MHD a s mo&#x17E;nost&#xED; ulo&#x17E;en&#xED; adresy pod vlastn&#xED;m n&#xE1;zvem (Doma, Pr&#xE1;ce...)<br>&#x2605; Automatick&#xE9; aktualizace j&#xED;zdn&#xED;ch &#x159;&#xE1;d&#x16F; p&#x159;es Wi-Fi<br>&#x2605; P&#x159;izp&#x16F;soben&#xED; pro tablety<br>&#x2605; Samostatn&#xE1; aplikace pro hodinky Android Wear<br><br>Data poskytuj&#xED; spole&#x10D;nosti CHAPS spol. s r.o. a Inprop s.r.o.<br>Za vytvo&#x159;en&#xED; seznamu GPS sou&#x159;adnic pro MHD Ko&#x161;ice d&#x11B;kujeme u&#x17E;ivateli J&#xFA;liu Kundr&#xE1;tovi.<br><br>CENA:<br><br>Samotn&#xE1; aplikace je k dispozici ke sta&#x17E;en&#xED; zdarma. Za datov&#xE9; soubory j&#xED;zdn&#xED;ch &#x159;&#xE1;d&#x16F; se plat&#xED; ro&#x10D;n&#xED; licen&#x10D;n&#xED; poplatek. J&#xED;zdn&#xED; &#x159;&#xE1;dy je mo&#x17E;n&#xE9; nakupovat bu&#x10F; jednotliv&#x11B; nebo je mo&#x17E;n&#xE9; zakoupit zv&#xFD;hodn&#x11B;n&#xE9; bal&#xED;&#x10D;ky pro &#x10C;eskou a Slovenskou republiku a evropsk&#xE9; vlaky. Aktu&#xE1;ln&#xED; cen&#xED;k naleznete na webov&#xFD;ch str&#xE1;nk&#xE1;ch aplikace:<br>http://www.cgtransit.cz<br><br>AKCE - nov&#xED; u&#x17E;ivatel&#xE9; maj&#xED; m&#x11B;s&#xED;c na vyzkou&#x161;en&#xED; v&#x161;ech j&#xED;zdn&#xED;ch &#x159;&#xE1;d&#x16F; zdarma<br><br>*** Pokud m&#xE1;te s aplikac&#xED; probl&#xE9;m, napi&#x161;te n&#xE1;m pros&#xED;m na email android@cgtransit.com - pokud nap&#xED;&#x161;ete probl&#xE9;m do hodnocen&#xED; aplikace, nem&#x16F;&#x17E;eme ho vy&#x159;e&#x161;it. D&#xED;ky. ***",
    "histogram": {
        "1": 301,
        "2": 107,
        "3": 192,
        "4": 759,
        "5": 5810
    },
    "offersIAP": true,
    "adSupported": false,
    "androidVersionText": "4.0 and up",
    "androidVersion": "4.0",
    "contentRating": "Everyone",
    "screenshots": [
        "//lh4.ggpht.com/cXUKo41J_t8a7rMF7PbvYOvZrN-IAXC07-tygRC_t0dPEBdjsxK4nMvkMgnDR6z-KviZ=h310",
        "//lh5.ggpht.com/x-4Ph7QCDrph8h5XgCIk8f0bOlIigV9oR_1n-BcKoduwK7MJ8fCcNlUf5hYTQFXwOxQ=h310",
        "//lh6.ggpht.com/qxZdqWw5VNsCbCCp-rDQNxI8M3bDsSgzr6EWi1myzD1OOaf6hPlR_xzl7fa_ZW1-ig=h310",
        "//lh4.ggpht.com/HtPGquzw9P_34_UzSJz0F9iIIWR0qZDrLlHUEWYOlFGE3QtRvZPkz07jccnArdnFLpvR=h310",
        "//lh4.ggpht.com/LfsWJXDOjl1WIgCP9nKwG9ZJjFfuv82uUiJT4enW2x6hXMSBBmk3plZxnuBdHsoYzIM=h310",
        "//lh6.ggpht.com/nYDFJT2KyTMTbKtywPbv-hs8dfHoZ6nJwipVrTpKh95ns5B5PS_0uNsrT5CHZZ_cWQ=h310",
        "//lh3.ggpht.com/aaOAowtaaMqn2_VfGjbFDpNmkNjn_YgFOlnMdbGRFrKkRs8ZOyeBa2Vmcehdptl7GMOP=h310",
        "//lh5.ggpht.com/MUpcpVyyAwyz2OQg9CrzTZqLWYKA6UisY2X7QPYCXvZE8AYpjom4kJd9l5WudPv3MA=h310",
        "//lh3.ggpht.com/wdlrGdxIuUFqe1rpw2gqEqwWR3rLl1Pi57mLFxWYMxMZcKbOMUIwxUAYJE6L0WfY9w=h310",
        "//lh3.ggpht.com/_qbk69or8FNvGXZnTDPTLlc3GZc6IAN0v4AqORbCint-87fImXkLPw-ElZEY5QyQEA=h310",
        "//lh3.ggpht.com/jKtgPCRys1C2pl2UFsfH-XgviGaLKGa_kuuxcdVFJNN6rKxDdE_gBEVFOdtvkQ01N0uh=h310",
        "//lh5.ggpht.com/KlzYUKcCnbVXEjhv0io-XerYAeMAJoJNocnAlOqH2hljOaipRylpPSqaqsKXv4xVE2U=h310",
        "//lh4.ggpht.com/qzFl3PGnDtirQKxzZmp09rvy_fnAGzZtEN5xuMtrov-WyPp5RBgccYiaRuJpDKCjT48=h310",
        "//lh6.ggpht.com/HAL0kByAXpchenEYt6R4w8VGoF4F_GE1d2BA951hLZotA4yP4pDzWNwK37fXJV5BoiJz=h310",
        "//lh3.ggpht.com/0Rzpq4BfvLJeKAZr5mapXzToqzDoQhvR6Vcx35B-O-vZi6SDXS-fx9md6wDxyayN8ZU=h310",
        "//lh4.ggpht.com/d49aoTxigIe_ZPRjWLs5Rnoi4-M7vMurX7FolJeFrJfOo-sWdMQ01SY_6fRx5ZZxrUI=h310",
        "//lh5.ggpht.com/KxhZIxS6jBDZVQab8oi4tpkhg4_RsbccQO5ILwY82HrglrKkp_egasRhMqTWCcsk36s=h310",
        "//lh3.ggpht.com/oEbWp3tBGTj9UH6c3tKMpuh9Wp8AB7ayM-KZP439h3zCr41ll9UqrcECKQda7MfXZmg=h310",
        "//lh6.ggpht.com/4d18hW4cJ82XoloVb2tRTJFCMI45iYNxKiGH59I5tchJWCnJkwrwVaoHWm2ZGG2ment-=h310",
        "//lh5.ggpht.com/qtCeedwDMY8j4RwemYPrA-5wmVWKf0MYSMvWA_N181IGsoI42N2PcdG2Es8n1dEenwrw=h310",
        "//lh3.ggpht.com/6jSg2BlnAyfqMo6MpmMv5rfAqiOGkzPjy-WJdb90RXb8LjNXrXhukM9LqWwW8Q6kb8Y=h310",
        "//lh5.ggpht.com/wJREXGXjbTq4Wk9LxMFF7uPitArPdFu5MBKKFtX3LYTTnGUABa3LNiWUsp6yED6_yg=h310",
        "//lh6.ggpht.com/LFrrDKO2pyI4401muDMNbB_WCItitP4FkCYmedZkl_fCSb07YQAcFSPSs4oQib1Jjw=h310",
        "//lh3.ggpht.com/3UkUNqarm-VfqxgRcbI9SYihqbHlJ0TwQl2y5YfU8i5ZCoUjUoApFgzTSyMYzl09zKBd=h310",
        "//lh3.googleusercontent.com/O9jnD8ATPdaftbMEVzQY-UM58V6__Y9yiU7ugWCeJwxvKy7AsrCK0Uyibo3fOz6SnG0=h310",
        "//lh3.googleusercontent.com/bpHFCGXZThUkncRi_OCRxZ-rVTT5gr8JqXiQyb7dG4KmpP0LtzhdL7xPEsrSA_Vvdg=h310",
        "//lh3.googleusercontent.com/XHoekQ2YoIY6pz_CK4oTr336FMknm0eyT5_vtyezKc-sB7F36WrSX2BhUT7-H7bKfTw=h310"
    ],
    "comments": [
        "Best best best Well, the fact that it works offline, updates fast and has configuration options makes it great. If you didn't know, you can swipe left or right to see the previous or next entry. I don't buy apps often but having multiple countries for just a few euros per year  is worth it for sure.",
        "Perfect app for years. Nevertheless, last days it downloads wrong (or obsolete?) timetables in Prague. E.g. tram n. 9, more times. Please fix this, it has no sense when it shows wrong wrong timetables for some lines.",
        "Perfect offline IDOS The timetables needs to be purchased, but you get 30 day free trial of all available timetables and for me, €3 is okay price to have all public transport in Czech Republic on the go in offline. The design seems neat and professionally done. I also appreciate there are no ads or rate-the-app pop-ups.",
        "Bad time picker It's difficult to set right time of arrive or departure. Anyway, the application is great",
        "Cannot live without it Using it everyday. Still wondering how intuitive is its usage. It is must have if you use any form of public traffic regularly.",
        "Horrible updates, incomplete info The only benefit is offline usage. Updates are very late, incomplete info about changing trams, you have to know the place well in order not to waste your time."
    ],
    "recentChanges": [],
    "preregister": false,
    "url": "https://play.google.com/store/apps/details?id=com.circlegate.tt.transit.android&hl=en&gl=us",
    "appId": "com.circlegate.tt.transit.android"
}